spatial_detector/__init__.py
spatial_detector/cli/__init__.py
spatial_detector/cli/webcam_app.py
spatial_detector/depth/__init__.py
spatial_detector/depth/midas_depth.py
spatial_detector/detection/__init__.py
spatial_detector/detection/yolo_detector.py
spatial_detector/projection/__init__.py
spatial_detector/projection/camera_model.py
spatial_detector/visualization/__init__.py
spatial_detector/visualization/visualizer.py
spatial_detector-0.1.0.dist-info/METADATA
spatial_detector-0.1.0.dist-info/WHEEL
spatial_detector-0.1.0.dist-info/entry_points.txt
spatial_detector-0.1.0.dist-info/licenses/LICENSE
spatial_detector-0.1.0.dist-info/RECORD
