Metadata-Version: 2.4
Name: spatial-detector
Version: 0.1.0
Summary: 3D object detection and spatial mapping using webcam
Project-URL: Homepage, https://github.com/oldhero5/spatial-detector
Project-URL: Bug Tracker, https://github.com/oldhero5/spatial-detector/issues
Author-email: Marty H <oldhero5@proton.me>
License-File: LICENSE
Classifier: License :: OSI Approved :: MIT License
Classifier: Operating System :: OS Independent
Classifier: Programming Language :: Python :: 3
Requires-Python: >=3.7
Requires-Dist: matplotlib>=3.5.0
Requires-Dist: numpy>=1.19.0
Requires-Dist: opencv-python>=4.5.0
Requires-Dist: timm==0.6.13
Requires-Dist: torch>=1.13.0
Requires-Dist: torchvision>=0.14.0
Requires-Dist: tqdm>=4.64.0
Requires-Dist: ultralytics>=8.0.0
